mc145000/verilog/project_1.srcs/sources_1/new/mc145ksys.v
`timescale 1ns / 1ps
//////////////////////////////////////////////////////////////////////////////////
// Company: 
// Engineer: 
// 
// Create Date: 02/07/2020 10:12:15 AM
// Design Name: 
// Module Name: mc145ksys
// Project Name: 
// Target Devices: 
// Tool Versions: 
// Description: 
// 
// Dependencies: 
// 
// Revision:
// Revision 0.01 - File Created
// Additional Comments:
// 
//////////////////////////////////////////////////////////////////////////////////

module mc145ksys(
    input clk,
    input i_data,
    output reg o_data,
    input write_en,
    output reg [7:0] o_io = 0,
    output reg [3:0] o_inst,
    input [7:0] i_io
    );
    reg [7:0] ram = 0;
    reg [7:0] rom [511:0];
    reg [8:0] pc = 0;
    initial $readmemh("rom.mem", rom);
    always @(negedge clk) begin
        // update instruction
        o_inst <= rom[pc][7:4];
        if (write_en) begin
            // we have to set the address from the ROM to i_data;
            if (rom[pc][3:0] > 7) // If it's accessing RAM
                ram[rom[pc][3:0] - 'h8] <= i_data;
            else
                o_io[rom[pc][3:0]] <= i_data;

        end else begin
            // we are not writing, so get the address and load it to o_data;
            if (rom[pc][3:0] > 7) // If it's accessing RAM
                 o_data <= ram[rom[pc][3:0] - 'h8];
            else // Accessing inputs.
                o_data <= i_io[rom[pc][3:0]];
        end
        pc <= pc + 1;
    end
endmodule

mc145000/verilog/project_1.srcs/sim_1/new/sim_mc145ksys.v
`timescale 1ns / 1ps
//////////////////////////////////////////////////////////////////////////////////
// Company: 
// Engineer: 
// 
// Create Date: 02/07/2020 03:06:45 PM
// Design Name: 
// Module Name: sim_mc145ksys
// Project Name: 
// Target Devices: 
// Tool Versions: 
// Description: 
// 
// Dependencies: 
// 
// Revision:
// Revision 0.01 - File Created
// Additional Comments:
// 
//////////////////////////////////////////////////////////////////////////////////


module sim_mc145ksys();
    reg clk = 0, write = 0, i_data = 0;
    wire [7:0] out;
    wire o_data;
    wire [3:0] inst;
    reg [7:0] in = 0;
    mc145ksys DUT(clk, i_data, o_data, write, out, inst, in);
    always begin
        #5 clk = ~clk;
    end
    initial begin
        $dumpvars;
        repeat(16) @(posedge clk);
        i_data <= 1;
        write <= 1;
        repeat(16) @(posedge clk);
        i_data <= 0;
        repeat(16) @(posedge clk);
        // inst should be
        $finish;
    end
endmodule

mc145000/verilog/project_1.sim/sim_1/behav/xsim/dump.vcd
$date
   Sat Feb  8 14:29:55 2020
$end
$version
  2019.2
$end
$timescale
  1ps
$end
$scope module sim_mc145ksys $end
$var reg 1 ! clk $end
$var reg 1 " write $end
$var reg 1 # i_data $end
$var wire 8 $ out [7:0] $end
$var wire 1 % o_data $end
$var wire 4 & inst [3:0] $end
$var reg 8 ' in [7:0] $end
$scope module DUT $end
$var wire 1 ( clk $end
$var wire 1 ) i_data $end
$var reg 1 * o_data $end
$var wire 1 + write_en $end
$var reg 8 , o_io [7:0] $end
$var reg 4 - o_inst [3:0] $end
$var wire 8 . i_io [7:0] $end
$var reg 8 / ram [7:0] $end
$var reg 9 0 pc [8:0] $end
$upscope $end
$upscope $end
$enddefinitions $end
#0
$dumpvars
0!
0"
0#
b0 $
0%
b0 &
b0 '
0(
0)
0*
0+
b0 ,
b0 -
b0 .
b0 /
b1 0
$end
#5000
1!
1(
#10000
0!
b1 &
0(
0*
b1 -
b10 0
#15000
1!
1(
#20000
0!
b10 &
0(
0*
b10 -
b11 0
#25000
1!
1(
#30000
0!
b11 &
0(
0*
b11 -
b100 0
#35000
1!
1(
#40000
0!
b100 &
0(
0*
b100 -
b101 0
#45000
1!
1(
#50000
0!
b101 &
0(
0*
b101 -
b110 0
#55000
1!
1(
#60000
0!
b110 &
0(
0*
b110 -
b111 0
#65000
1!
1(
#70000
0!
b111 &
0(
0*
b111 -
b1000 0
#75000
1!
1(
#80000
0!
b1000 &
0(
0*
b1000 -
b1001 0
#85000
1!
1(
#90000
0!
b1001 &
0(
0*
b1001 -
b1010 0
#95000
1!
1(
#100000
0!
b1010 &
0(
0*
b1010 -
b1011 0
#105000
1!
1(
#110000
0!
b1011 &
0(
0*
b1011 -
b1100 0
#115000
1!
1(
#120000
0!
b1100 &
0(
0*
b1100 -
b1101 0
#125000
1!
1(
#130000
0!
b1101 &
0(
0*
b1101 -
b1110 0
#135000
1!
1(
#140000
0!
b1110 &
0(
0*
b1110 -
b1111 0
#145000
1!
1(
#150000
0!
b1111 &
0(
0*
b1111 -
b10000 0
#155000
1!
1"
1#
1(
1)
1+
#160000
0!
b1 $
b1 &
0(
b1 ,
b1 -
b10001 0
#165000
1!
1(
#170000
0!
b11 $
0(
b11 ,
b1 -
b10010 0
#175000
1!
1(
#180000
0!
b111 $
0(
b111 ,
b1 -
b10011 0
#185000
1!
1(
#190000
0!
b1111 $
0(
b1111 ,
b1 -
b10100 0
#195000
1!
1(
#200000
0!
b11111 $
0(
b11111 ,
b1 -
b10101 0
#205000
1!
1(
#210000
0!
b111111 $
0(
b111111 ,
b1 -
b10110 0
#215000
1!
1(
#220000
0!
b1111111 $
0(
b1111111 ,
b1 -
b10111 0
#225000
1!
1(
#230000
0!
b11111111 $
0(
b11111111 ,
b1 -
b11000 0
#235000
1!
1(
#240000
0!
0(
b1 -
b1 /
b11001 0
#245000
1!
1(
#250000
0!
0(
b1 -
b11 /
b11010 0
#255000
1!
1(
#260000
0!
0(
b1 -
b111 /
b11011 0
#265000
1!
1(
#270000
0!
0(
b1 -
b1111 /
b11100 0
#275000
1!
1(
#280000
0!
0(
b1 -
b11111 /
b11101 0
#285000
1!
1(
#290000
0!
0(
b1 -
b111111 /
b11110 0
#295000
1!
1(
#300000
0!
0(
b1 -
b1111111 /
b11111 0
#305000
1!
1(
#310000
0!
0(
b1 -
b11111111 /
b100000 0
#315000
1!
0#
1(
0)
#320000
0!
b11111110 $
0(
b11111110 ,
b1 -
b100001 0
#325000
1!
1(
#330000
0!
b11111100 $
0(
b11111100 ,
b1 -
b100010 0
#335000
1!
1(
#340000
0!
b11111000 $
0(
b11111000 ,
b1 -
b100011 0
#345000
1!
1(
#350000
0!
b11110000 $
0(
b11110000 ,
b1 -
b100100 0
#355000
1!
1(
#360000
0!
b11100000 $
0(
b11100000 ,
b1 -
b100101 0
#365000
1!
1(
#370000
0!
b11000000 $
0(
b11000000 ,
b1 -
b100110 0
#375000
1!
1(
#380000
0!
b10000000 $
0(
b10000000 ,
b1 -
b100111 0
#385000
1!
1(
#390000
0!
b0 $
0(
b0 ,
b1 -
b101000 0
#395000
1!
1(
#400000
0!
0(
b1 -
b11111110 /
b101001 0
#405000
1!
1(
#410000
0!
0(
b1 -
b11111100 /
b101010 0
#415000
1!
1(
#420000
0!
0(
b1 -
b11111000 /
b101011 0
#425000
1!
1(
#430000
0!
0(
b1 -
b11110000 /
b101100 0
#435000
1!
1(
#440000
0!
0(
b1 -
b11100000 /
b101101 0
#445000
1!
1(
#450000
0!
0(
b1 -
b11000000 /
b101110 0
#455000
1!
1(
#460000
0!
0(
b1 -
b10000000 /
b101111 0
#465000
1!
1(
#470000
0!
0(
b1 -
b0 /
b110000 0
